picarto/__init__.py
picarto/api.py
picarto/category.py
picarto/channel.py
picarto/client.py
picarto/errors.py
picarto.py-0.1.0.dist-info/DESCRIPTION.rst
picarto.py-0.1.0.dist-info/METADATA
picarto.py-0.1.0.dist-info/RECORD
picarto.py-0.1.0.dist-info/WHEEL
picarto.py-0.1.0.dist-info/metadata.json
picarto.py-0.1.0.dist-info/top_level.txt
